pyoma2/__init__.py
pyoma2/algorithms/__init__.py
pyoma2/algorithms/base.py
pyoma2/algorithms/data/mpe_params.py
pyoma2/algorithms/data/result.py
pyoma2/algorithms/data/run_params.py
pyoma2/algorithms/fdd.py
pyoma2/algorithms/plscf.py
pyoma2/algorithms/ssi.py
pyoma2/functions/__init__.py
pyoma2/functions/clus.py
pyoma2/functions/fdd.py
pyoma2/functions/gen.py
pyoma2/functions/plot.py
pyoma2/functions/plscf.py
pyoma2/functions/ssi.py
pyoma2/setup/__init__.py
pyoma2/setup/base.py
pyoma2/setup/multi.py
pyoma2/setup/single.py
pyoma2/support/__init__.py
pyoma2/support/geometry/__init__.py
pyoma2/support/geometry/data.py
pyoma2/support/geometry/mixin.py
pyoma2/support/geometry/mpl_plotter.py
pyoma2/support/geometry/plotter.py
pyoma2/support/geometry/pyvista_plotter.py
pyoma2/support/sel_from_plot.py
pyoma2/support/utils/logging_handler.py
pyoma2/support/utils/sample_data.py
pyoma2/support/utils/typing.py
pyoma_2-1.2.1.dist-info/METADATA
pyoma_2-1.2.1.dist-info/WHEEL
pyoma_2-1.2.1.dist-info/entry_points.txt
pyoma_2-1.2.1.dist-info/licenses/LICENSE
pyoma_2-1.2.1.dist-info/RECORD
