Metadata-Version: 2.1
Name: pyOMA_2
Version: 1.2.1
Summary: Python module for conducting Operational Modal Analysis
Author-Email: Dag Pasca <dpa@treteknisk.no>, Angelo Aloisio <angelo.aloisio1@univaq.it>, Marco Martino Rosso <marco.rosso@polito.it>, Diego Federico Margoni <diegofederico.margoni@studenti.polito.it>
License: MIT
Project-URL: Homepage, https://github.com/dagghe/pyOMA2
Project-URL: Documentation, https://pyoma.readthedocs.io/en/main/
Project-URL: Repository, https://github.com/dagghe/pyOMA2
Project-URL: Changelog, https://github.com/dagghe/pyOMA2/blob/main/CHANGELOG.md
Project-URL: Contributing, https://github.com/dagghe/pyOMA2/blob/main/CONTRIBUTING.md
Requires-Python: <3.13,>=3.8
Requires-Dist: numpy<1.25,>=1.20; python_version < "3.9"
Requires-Dist: numpy>=1.25; python_version >= "3.9"
Requires-Dist: pandas>=2.0.3
Requires-Dist: scipy>=1.9.3
Requires-Dist: pydantic>=2.5.1
Requires-Dist: tqdm>=4.66.1
Requires-Dist: matplotlib>=3.7.4
Requires-Dist: pyvista[all]
Requires-Dist: pyvistaqt
Requires-Dist: PyQt5==5.15.10
Requires-Dist: PyQt5-Qt5==5.15.2; sys_platform != "darwin"
Requires-Dist: PyQt5-Qt5==5.15.14; sys_platform == "darwin"
Requires-Dist: PyQt5-sip==12.15.0
Requires-Dist: vtk==9.3.1; python_version != "3.8" or sys_platform != "darwin"
Requires-Dist: openpyxl>=3.1.3
Requires-Dist: scikit-learn>=1.3.2
